llm_tools_brave.py
llm_tools_brave-0.1.0.dist-info/METADATA
llm_tools_brave-0.1.0.dist-info/WHEEL
llm_tools_brave-0.1.0.dist-info/entry_points.txt
llm_tools_brave-0.1.0.dist-info/top_level.txt
llm_tools_brave-0.1.0.dist-info/RECORD
