Metadata-Version: 2.4
Name: llm-tools-brave
Version: 0.1.0
Summary: A tool plugin for LLM to enable web search with Brave Search API
Author-email: Ian Langworth <ian@langworth.com>
License-Expression: MIT
Requires-Python: >=3.9
Requires-Dist: httpx>=0.24.0
Requires-Dist: llm>=0.26
Requires-Dist: pytest>=8.3.5
Provides-Extra: test
Requires-Dist: pytest>=8.3.5; extra == "test"
